{
    "tngMobile/consumer/get-pending-item-list": {
        "status": "success",
        "errorCode": null,
        "errorEN": null,
        "errorZhHK": null,
        "errorZhCN": null,
        "action": null,
        "pendingItems:19": {
            "id": "[1+1!:castoff]",
            "templateId": "[1+1]",
            "type": "ActivityHistory",
            "detail": {
                "id": "[1+1!:castoff]",
                "consumerId": "[11+6]bfd0a6-[15+5]a2-4e3c-9fa5-bb7f8f8555fa",
                "consumerPic": "../commonTemplate/img/_dev/[1-7].ico",
                "nickName": "[@{2}]",
                "activityTitle": "[@{3}]",
                "type": "[P2P sender request+P2P receiver request+Global Remit+Global Bill Pay+Global SIM Top up+Foreign Exchange+ID Uploaded+ID Rejected+Credit Card Upload+Credit Card Reject+Bank account Upload+Bank account Reject+Email address Upload+Email address Reject+CDD appointment reminder+Fast Pay setup promotion+Coupon about to expire+Ticket about to expire+Duplicate login Notification]",
                "counterpartType": "MERCHANT",
                "counterpartId": "200",
                "createDatetime": "2017-06-12 09:27:45",
                "updateDatetime": "2017-06-12 09:27:45",
                "amount": "[(0-9)3].[(0-9)2]",
                "status": "COMPLETED",
                "refNo": "19214424",
                "remark": null,
                "enable": true,
                "jsonConent": "{\"RefundFXamount\":\"302.28\",\"FXcurrencyNameZhHK\":\"CNY\",\"ExchangeFXamount\":\"433\",\"FXcurrencyZhCN\":\"CNY\",\"ExchangeFXratio\":\"100:115.4875\",\"FXlocationZhCN\":\"[假数据]  尖沙咀弥敦道54-64号美丽都大厦地下42号铺\",\"FXcurrencyEN\":\"CNY\",\"CashoutBusinessHourEN\":\"Mon-Fri: 08:30-19:00 Sat: 08:30-18:00 Sun & Public holiday off\",\"MessageDateTime\":\"2017-06-12 09:27:44\",\"RefundFXratio\":\"100:116.0000\",\"FXlocationEN\":\"[假数据]  Shop No. 42, G/F, Mirador Mansion Arcade, 54-64 , Nathan Road,Tsim Sha Tsui, Kowloon.\",\"CollectFXExpiryDateTime\":\"2017-08-12 09:27:44\",\"ExpiryFXRefNo\":\"TT019214424\",\"CollectFXRefNo\":\"TT019209171\",\"FXcurrencyNameZhCN\":\"CNY\",\"FXExpiredAdminFee\":\"200\",\"CollectFXDateTime\":\"2017-06-07 15:24:15\",\"CashoutBusinessHourZhHK\":\"Mon-Fri: 08:30-19:00 Sat: 08:30-18:00 Sun & Public holiday off\",\"CashoutBusinessHourZhCN\":\"Mon-Fri: 08:30-19:00 Sat: 08:30-18:00 Sun & Public holiday off\",\"FXlocationZhHK\":\"[假数据]  尖沙咀彌敦道54-64號美麗都大廈地下42號舖\",\"FXcurrencyZhHK\":\"CNY\",\"FXcurrencyNameEN\":\"CNY\",\"CollectFXamount\":\"500.07\",\"CancelFXamount\":\"502.28\"}"
            }
        }
    },
    "tngMobile/consumer/delete-pending-item": {
        "status": "success",
        "errorCode": null,
        "errorEN": null,
        "errorZhHK": null,
        "errorZhCN": null,
        "action": null
    }
}