{
    "status": "success",
    "errorCode": null,
    "errorEN": null,
    "errorZhHK": null,
    "errorZhCN": null,
    "errorIND": null,
    "errorPHI": null,
    "action": null,
    "branches": [
        {
            "id": 137562,
            "code": "939200",
            "name": "AMP Bank Limited"
        },
        {
            "id": 137563,
            "code": "939300",
            "name": "AMP Bank Limited"
        },
        {
            "id": 137566,
            "code": "939600",
            "name": "AMP Bank Limited"
        },
        {
            "id": 137565,
            "code": "939500",
            "name": "AMP Bank Limited"
        },
        {
            "id": 137564,
            "code": "939400",
            "name": "AMP Bank Limited"
        }
    ]
}