{
    "id": 20731521,
    "consumerId": "55d859c2-65aa-4e47-80bf-16898d08e7f2",
    "type": "GLOBAL_REMITTANCE",
    "counterpartType": "MERCHANT",
    "counterpartId": "9999",
    "createDatetime": "2018-02-07 16:47:00",
    "updateDatetime": "2018-02-07 16:47:00",
    "amount": -735,
    "status": "COMPLETED",
    "refNo": "TT020726164",
    "remark": null,
    "enable": true,
    "profileId": 3097,
    "jsonConent": {
        "tx_ref_no": "TT020726164",
        "ProfileType": "other",
        "Method": "GBT",
        "RemitMethodEN": "Bank Transfer",
        "RemitAmount": "610.89",
        "TransactionColor": "GREY",
        "CurrencyType": "CNY",
        "RemitteeMobile": "8521112222",
        "statusId": "AwaitingConfirmation",
        "RemitteeReceiverLastName": "习",
        "grProfileId": "3521",
        "RemitMethodTC": "銀行轉賬",
        "RemitteeReceiverFirstName": "近平",
        "submission_Date_n_Time": "2018-02-07 16:47:00",
        "RemitMethodSC": "银行转账",
        "screeningQueueId": 3990,
        "friendProfileId": "3097",
        "ForeignAmount": "610.89",
        "remittance_ref_no": "TT020726164"
    },
    "templateId": 407,
    "listingTemplateId": 1001,
    "cardTemplateId": 407,
    "template": {
        "id": 407,
        "templateName": "Request Supplement (global remittance)",
        "titleEn": "Supplementary Information",
        "titleZhHK": "補交匯款資料",
        "titleZhCN": "补交汇款资料",
        "titleIDN": "Informasi Tambahan",
        "titlePHL": "Supplementary Information",
        "templateEN": "Request Receiver Supplementary Information. Ref. No. <%tx_ref_no%>",
        "templateZhHK": "需要補交匯款收款人資料。匯款參考編號：<%tx_ref_no%>",
        "templateZhCN": "需要补交汇款收款人资料。汇款参考编号：<%tx_ref_no%>",
        "templateIDN": "No. Ref. Permintaan Informasi Tambahan Penerima. <%tx_ref_no%>",
        "templatePHL": "Content_355",
        "icon": null,
        "templateDtlEN": null,
        "templateDtlZhHK": null,
        "templateDtlZhCN": null,
        "templateDtlIDN": null,
        "templateDtlPHL": null,
        "createDatetime": "2017-10-04 15:32:19",
        "updateDatetime": "2017-10-04 15:32:19",
        "enable": true,
        "tabField": "<%RemitMethod%>,<%RemitSubmitDate&Time%>,<%RemitTNGAmount%>,<%RemitRatio%>,<%RemitAmount%>,<%RemitAdminFee%>,<%RemitSubmitRefNo%>,<%RemitStatus%>,<%RemitRemarks%>",
        "title": "Supplementary Information"
    },
    "jsonContent": "{\"tx_ref_no\":\"TT020726164\",\"ProfileType\":\"other\",\"Method\":\"GBT\",\"RemitMethodEN\":\"Bank Transfer\",\"RemitAmount\":\"610.89\",\"TransactionColor\":\"GREY\",\"CurrencyType\":\"CNY\",\"RemitteeMobile\":\"8521112222\",\"statusId\":\"AwaitingConfirmation\",\"RemitteeReceiverLastName\":\"习\",\"grProfileId\":\"3521\",\"RemitMethodTC\":\"銀行轉賬\",\"RemitteeReceiverFirstName\":\"近平\",\"submission_Date_n_Time\":\"2018-02-07 16:47:00\",\"RemitMethodSC\":\"银行转账\",\"screeningQueueId\":3990,\"friendProfileId\":\"3097\",\"ForeignAmount\":\"610.89\",\"remittance_ref_no\":\"TT020726164\"}",
    "unread": false
}